[
	{
		"name": "SOBRE N\u00d3S",
		"cover_url": "https://scontent.fpoa12-1.fna.fbcdn.net/v/t1.0-0/s526x296/51218495_776052489430912_6733385672079441920_n.jpg?_nc_cat=110&_nc_ht=scontent.fpoa12-1.fna&oh=a1ecde09247464bcc15cbdc676cd9b40&oe=5D4D6FD5",
		"address": "Andradas 736, 90020-004 Porto Alegre",
		"datetimes": [
			"2019-06-06 20:00:00",
			"2019-06-07 20:00:00",
			"2019-06-12 20:00:00"
		],
		"dates": [
			"Saturday, April 6, 2019",
			"Sunday, April 7, 2019",
			"Friday, April 12, 2019"
		],
		"times": [
			" 8:00 PM",
			" 8:00 PM",
			" 8:00 PM"
		],
		"place": "Casa De Cultura Mario Quintana",
		"organizers": [
			"SOBRE N\u00d3S"
		],
		"organizers_fallback_a": [
			"Casa De Cultura Mario Quintana"
		],
		"description": "<span>ESCOLHA A DATA E CONFIRME SUA PRESEN\u00c7A!<br><br>SINOPSE:<br>Partindo dos textos de Tchekhov  a pe\u00e7a apresenta um paralelo dos cl\u00e1ssicos com a vida cotidiana. Os anseios sociais e pol\u00edticos atuais atravessam as figuras que buscam por algum lugar e terminam por encontrar a inexist\u00eancia dele, mantendo a poesia melanc\u00f3lica potente do autor. Como no Tetris, jogo criado nos anos 80 na R\u00fassia, a trama acontece atrav\u00e9s de um conjunto de fragmentos que se encaixam dando uma possibilidade contempor\u00e2nea de leitura sobre quais s\u00e3o as reais quest\u00f5es que te afetam hoje. Qual \u00e9 a \u201csua R\u00fassia\u201d?<br><br>SERVI\u00c7O:<br>Temporada \u201cSOBRE N\u00d3S\u201d: De 5 a 28 de abril<br>Sextas, s\u00e1bado e domingos \u00e0s 20h<br>Teatro Carlos Carvalho \u2013 Casa de Cultura Mario Quintana<br><br>Ingressos de plateia VIP por R$ 50 e recompensas em financiamento coletivo atrav\u00e9s do link: <a  href=\"https://bit.ly/AjudaSobreNos\" rel=\"nofollow\" >http://bit.ly/AjudaSobreNos</a><br> <br>FICHA T\u00c9CNICA:<br>Dire\u00e7\u00e3o: Leo Maciel<br>Prepara\u00e7\u00e3o corporal/coreografia: Angela Spiazzi<br>Produ\u00e7\u00e3o: Jaques Machado<br>Design de luz: Ricardo Vivian<br>Operadora de som: Manu Goulart<br>Figurinos, Maquiagem e Cabelos: Valquiria Cardoso<br><br>Elenco: Aline Armani, Felipe Evangelista, Guilherme Fraga, Jaques Machado, Juliana Sixel, Lincoln Speziali, Natalia Lavratti e Ricardo Neme.<br><br>Dura\u00e7\u00e3o: 75 minutos<br>Classifica\u00e7\u00e3o: 12 anos.<br></span>",
		"prices": [
			"17",
			"50"
		],
		"categories": [
			"Art",
			"Drama (theater)",
			"Comedy (theater)"
		],
		"source_url": "https://www.facebook.com/events/308287106545395"
	},
	{
		"name": "Feira de P\u00e1scoa",
		"cover_url": "https://scontent.fpoa12-1.fna.fbcdn.net/v/t1.0-0/p280x280/56869956_2341806709218063_6013799287870193664_n.jpg?_nc_cat=104&_nc_ht=scontent.fpoa12-1.fna&oh=79382c9ad0bbbad8879ed9a19b6963f3&oe=5D0960C7",
		"address": "Andradas 736, 90020-004 Porto Alegre",
		"datetimes": [
			"2019-06-17 10:00:00"
		],
		"place": "Casa De Cultura Mario Quintana",
		"organizers": [
			"La Movida Bazar Economia Criativa & Artes"
		],
		"organizers_fallback_a": [
			"Casa De Cultura Mario Quintana"
		],
		"description": "<span>O projeto La Movida  \u00e9 um evento itinerante de Economia Criativa que reune Arte, empreendedorismo , Moda, Gastronomia, M\u00fasica ,Criatividade  e Artesanato Sustent\u00e1vel e acontece desde 2015 em v\u00e1rios locais da cidade, inicialmente na Casa de Cultura M\u00e1rio quintana e a seguir nas v\u00e1rias pra\u00e7as e ruas da  da cidade.<br>Vem expor com a gente.</span>",
		"categories": [
			"Art"
		],
		"source_url": "https://www.facebook.com/events/583653305437569"
	},
	{
		"name": "Mercado de Pulgas Poa",
		"cover_url": "https://scontent.fpoa12-1.fna.fbcdn.net/v/t1.0-0/s526x296/55927982_2167472069984775_3138479001442451456_n.jpg?_nc_cat=108&_nc_ht=scontent.fpoa12-1.fna&oh=a17dffe03467e06748e51904a123c06d&oe=5D3F0E00",
		"address": "Andradas 736, 90020-004 Porto Alegre",
		"datetimes": [
			"2019-06-14 13:00:00"
		],
		"place": "Casa De Cultura Mario Quintana",
		"organizers": [
			"Mercado de Pulgas/POA",
			"Agora \u00e9 meu, Brech\u00f3",
			"YEAH - Brech\u00f3",
			"Carol Morandi Atelier Crochet"
		],
		"organizers_fallback_a": [
			"Casa De Cultura Mario Quintana"
		],
		"description": "<span>Nossa Feira aterriza novamente na Casa de Cultura Mario Quintana como um grande mercado do alternativo, vintage e cultural.<br>Como sempre teremos expositores dos mais variados, um som gostoso e nost\u00e1lgico e algumas atra\u00e7\u00f5es!<br><br>A arara convidada desta vez fica por conta da querida Carol Morandi que traz sua linha de pe\u00e7as em croch\u00ea, a Carol Morandi Handmade Crochet, marca local que tamb\u00e9m ir\u00e1 fazer um desfile pocket em nosso evento!<br><br>Na finaleira n\u00e3o podia faltar o agito dos Teachers Trio na pista, tocando o melhor da Jovem Guarda! Pedida mais que confirmada!<br><br>N\u00e3o perde!<br><br>***Vai ser em <br>14/04 na Casa de Cultura Mario Quintana, Travessa dos Catavento<br>das 13h \u00e0s 19h<br><br>ENTRADA FRANCA<br><br>***16h Desfile pocket da marca Carol Morandi Handmade Crochet<br><br>***17h show com a banda Teachers Trio<br><br>/////Em caso de chuva o evento ser\u00e1 transferido\\\\\\\\\\<br><br>Tem uma marca, trabalho art\u00edstico, brech\u00f3 e que expor?<br>Entra em contato conosco pelo<br>mercadodepulgaspoa@gmail.com e manda teu portf\u00f3lio!<br><br>*Breve mais informa\u00e7\u00f5es S2<br></span>",
		"categories": [
			"Art",
			"Kid Friendly"
		],
		"source_url": "https://www.facebook.com/events/309311519729507"
	},
	{
		"name": "Picnic Cultural no Museu - Edi\u00e7\u00e3o n\u00ba18",
		"cover_url": "https://scontent.fpoa12-1.fna.fbcdn.net/v/t1.0-9/55600735_624461711315819_6084088227260530688_n.png?_nc_cat=109&_nc_ht=scontent.fpoa12-1.fna&oh=f2e54d80aa926d11255d04bbb59dba7f&oe=5D038193",
		"address": "Rua Jo\u00e3o Alfredo, 582, Porto Alegre",
		"datetimes": [
			"2019-06-28 12:00:00"
		],
		"place": "Picnic Cultural no Museu",
		"organizers": [
			"Gastronomia em movimento",
			"Museu de Porto Alegre Joaquim Felizardo",
			"Studio JAM"
		],
		"organizers_fallback_a": [
			"Picnic Cultural no Museu"
		],
		"description": "<span>\u2605 SALVE A DATA \u2605 <br><br>Essa edi\u00e7\u00e3o do Picnic Cultural no Museu ser\u00e1, como sempre, muito especial e cheia de coisas boas! <br><br>Vamos celebrar um dia lindo no p\u00e1tio do Museu de Porto Alegre Joaquim Felizardo. Um lugar cheio de energia positiva para tu curtires com teus amigos, amores e familiares! <br><br>\u21e8 Convida todo mundo e vem! :) <br><br>\u2605 O que \u00e9? \u2605 <br><br>Um evento gratuito com a inten\u00e7\u00e3o de ressignificar o espa\u00e7o do museu criando um elo entre a gastronomia, a m\u00fasica e a cidade, reinventando as rela\u00e7\u00f5es entre as artes e a vida.<br><br>\u2605 O que ter\u00e1? \u2605 <br><br>\u21e8 ESPA\u00c7O KIDS ! :) <br><br>\u21e8 M\u00daSICA de qualidade! ;) <br>\u266b \u266a \u266c Atra\u00e7\u00f5es \u266b \u266a \u266c<br><br>\u21e8 CERVEJAS ARTESANAIS<br><br>\u21e8 GASTRONOMIA de lamber os bei\u00e7o! <br><br>\u21e8 BAZAR e ARTESANATO<br><br>\u21e8 O MUSEU conta com um lindo ACERVO arqueol\u00f3gico da nossa querida Porto Alegre! E durante todo o evento as portas estar\u00e3o abertas para visitas! Atualmente, o Museu possui duas exposi\u00e7\u00f5es de longa dura\u00e7\u00e3o: \u201cO Solar que virou Museu \u2013 mem\u00f3rias e hist\u00f3rias\u201d, onde s\u00e3o exploradas as transforma\u00e7\u00f5es sofridas pela edifica\u00e7\u00e3o e trajet\u00f3ria dos indiv\u00edduos que a ela se relacionaram e \u201cTransforma\u00e7\u00f5es Urbanas: Porto Alegre de Montaury a Loureiro\u201d, dedicada \u00e0s mudan\u00e7as no espa\u00e7o da cidade.<br><br>At\u00e9 setembro de 2018 \u00e9 poss\u00edvel visitar a exposi\u00e7\u00e3o de curta dura\u00e7\u00e3o \u201cA Banda e a Cidade\u201d, dedicada \u00e0 Banda Municipal de Porto Alegre, criada em 1925 e at\u00e9 hoje em atividade. O p\u00fablico poder\u00e1 conferir os antigos uniformes, instrumentos musicais da primeira forma\u00e7\u00e3o do grupo, como o fagote e o trompete, al\u00e9m de partituras e imagens.<br><br>O acervo do Museu \u00e9 formado por cerca de 1.300 objetos dos s\u00e9culos XIX e XX, como acess\u00f3rios de uso pessoal, objetos de decora\u00e7\u00e3o, instrumentos musicais, mobili\u00e1rio e indument\u00e1ria, entre outros. Tamb\u00e9m conta com cerca de 200.000 itens arqueol\u00f3gicos relacionados a diferentes grupos que ocuparam o territ\u00f3rio desde o per\u00edodo pr\u00e9-colonial. Al\u00e9m disso, conta com, aproximadamente, 9.000 imagens da cidade de Porto Alegre dos s\u00e9culos XIX e XX.<br><br>Nessa edi\u00e7\u00e3o estaremos recolhendo doa\u00e7\u00f5es.<br><br>Informa\u00e7\u00f5es importantes:<br><br>- Alguns expositores podem n\u00e3o trabalhar com cart\u00f5es;<br>- N\u00e3o \u00e9 poss\u00edvel a entrada de animais, conforme norma interna do Museu; <br>- Somente ser\u00e1 permitida a entrada de alimentos e bebidas em por\u00e7\u00f5es individuais; <br>- Em caso de previs\u00e3o de chuva para o dia do evento ou chuvas recorrentes nos dias antecedentes, o evento poder\u00e1 ser adiado.<br><br>Chama teus amigos, teus vizinhos, teus primos, teus crushs e vem curtir este dia conosco! S\u00f3 n\u00e3o me chega em cima do la\u00e7o!!! <br><br>\u2605 ENTRADA FRANCA \u2605<br><br>Realiza\u00e7\u00e3o:<br><a  href=\"https://www.facebook.com/studiojampoa/\">Studio JAM</a>M<br><a  href=\"https://www.facebook.com/gastronomiaemmovimento/\">Gastronomia em movimento</a>imento<br><a  href=\"https://www.facebook.com/museudepoa/\">Museu de Porto Alegre Joaquim Felizardo</a> <br><br>Apoio:<br><a  href=\"https://www.facebook.com/updjs.net.br/\">UP Dee Jays</a><br>Prefeitura de Porto Alegre<br>Quer apoiar ou patrocinar o evento? Entre em contato conosco! ;)</span>",
		"categories": [
			"Art",
			"Kid Friendly",
			"Beer"
		],
		"source_url": "https://www.facebook.com/events/244934653035820"
	},
	{
		"name": "Serenata Iluminada na Virada Sustent\u00e1vel",
		"cover_url": "https://scontent.fpoa12-1.fna.fbcdn.net/v/t1.0-0/p526x296/53726462_2383959988281444_2252661663297699840_n.jpg?_nc_cat=102&_nc_ht=scontent.fpoa12-1.fna&oh=cb0b5c615714a8767775b5f069049c7e&oe=5D092CEF",
		"address": "Avenida Jo\u00e3o Pessoa, 90040-480 Porto Alegre",
		"datetimes": [
			"2019-06-06 18:00:00"
		],
		"place": "Reden\u00e7\u00e3o - Parque Farroupilha",
		"organizers": [
			"Serenata Iluminada",
			"Inser\u00e7\u00f5es em Circuitos Ideol\u00f3gicos",
			"Dona Concei\u00e7\u00e3o",
			"Edu Meirelles",
			"Cristian Sperandir",
			"Virada Sustent\u00e1vel Porto Alegre"
		],
		"organizers_fallback_a": [
			"Reden\u00e7\u00e3o - Parque Farroupilha"
		],
		"description": "<span>A Serenata Iluminada \u00e9 um movimento de pessoas que amam Porto Alegre e querem o melhor para a nossa cidade! Por isso, em abril estaremos mais uma vez juntos com a Virada Sustent\u00e1vel Porto Alegre 2019 para realizar uma edi\u00e7\u00e3o especial.<br><br>Teremos muitas atra\u00e7\u00f5es nessa noite, com a participa\u00e7\u00e3o que ter\u00e1 a apresenta\u00e7\u00e3o de quatro espet\u00e1culos - dois de m\u00fasica popular e outros dois de m\u00fasica instrumental, selecionados atrav\u00e9s do edital de ades\u00f5es da <a  href=\"https://www.facebook.com/viradasustentavelpoa/\">Virada Sustent\u00e1vel Porto Alegre</a>. Outros seis espet\u00e1culos musicais far\u00e3o parte da programa\u00e7\u00e3o geral.<br><br>A Serenata Iluminada surgiu em 2012 e segue muito viva: a ocupa\u00e7\u00e3o noturna do Parque Farroupilha, a Reden\u00e7\u00e3o, em prol de mais cultura, seguran\u00e7a cidad\u00e3 para que todos possam compartilhar o parque tamb\u00e9m \u00e0 noite. <br><br>Dessa forma, a Serenata Iluminada contribui para a reflex\u00e3o sobre os temas que norteiam a Virada 2019: redu\u00e7\u00e3o das desigualdades sociais, educa\u00e7\u00e3o de qualidade, cidades sustent\u00e1veis, colaboratividade, consumo respons\u00e1vel, \u00e1gua pot\u00e1vel e saneamento, paz, justi\u00e7a e institui\u00e7\u00f5es eficazes.<br><br>Traga velas, lanternas, instrumentos musicais e manifesta\u00e7\u00f5es culturais para fazer um encontro que mistura artes, alegria, express\u00e3o e reflex\u00e3o sobre o BOM USO dos espa\u00e7os p\u00fablicos de nossa cidade. Eles s\u00e3o NOSSOS! :) Traga sua LUZ, confirme presen\u00e7a e convide seus amigos, seus filhos, pais, leve o cachorro, a bici, os sorrisos... Enfim, traga muito AMOR e vamos nos divertir COM SABEDORIA.\"<br><br>Informa\u00e7\u00f5es b\u00e1sicas para uma boa confraterniza\u00e7\u00e3o em uma Serenata Iluminada para todos:<br><br>- Cuide do seu lixo, descarte os res\u00edduos no local correto e leve seus recicl\u00e1veis para casa; <br><br>- Respeite as diferen\u00e7as, saiba conviver com a diversidade de ideias; <br><br>- Compartilhe! Seja alegria, respeito, seja seu amor pela cidade; <br><br>- Fogo e \u00e1rvores n\u00e3o combinam. Tenha cuidado com o material que voc\u00ea vai levar para iluminar o parque, n\u00e3o fa\u00e7a fogo, \u00e9 proibido!<br><br>A Reden\u00e7\u00e3o \u00e9 de tod@s. Fa\u00e7a a sua parte, COLABORE no cuidado para que ningu\u00e9m cause danos aos canteiros, plantas, \u00e1rvores, sinaliza\u00e7\u00e3o, ilumina\u00e7\u00e3o e outros equipamentos! <a  href=\"https://www.facebook.com/hashtag/serenatailuminada\">#SerenataIluminada</a></span>",
		"categories": [
			"Art",
			"Kid Friendly",
			"Adult contemporary music"
		],
		"source_url": "https://www.facebook.com/events/373799036764008"
	},
	{
		"name": "Saint Patricks da CB - Torneio de Chopp a metro Grande Final",
		"cover_url": "https://scontent.fpoa12-1.fna.fbcdn.net/v/t1.0-0/s526x296/53845644_1081249398721413_3938617626137198592_n.jpg?_nc_cat=103&_nc_ht=scontent.fpoa12-1.fna&oh=5f4e2c88c305fc9ccd500be5c07fed24&oe=5D62BB03",
		"address": "90050-340 Porto Alegre",
		"datetimes": [
			"2019-09-22 14:00:00"
		],
		"place": "Cidade Baixa - POA",
		"organizers": [
			"Cumbia na Rua - Bailando sin Fronteras",
			"Instituto Parrhesia Erga Omnes",
			"CRAZY WORLD ARTS"
		],
		"organizers_fallback_a": [
			"Cidade Baixa - POA"
		],
		"description": "<span>Entonces devido a chuva transferimos a grande final do torneio de chopp a metro do Saint Patricks Days da CB, .pra a primavera;;;; Vem em busca do teu barril.... liga xs migxs... Viva la vida.....</span>",
		"categories": [
			"Art"
		],
		"source_url": "https://www.facebook.com/events/2217838035102664"
	},
	{
		"name": "Cumbia na Rua - Viralizando a Madrugada",
		"cover_url": "https://scontent.fpoa12-1.fna.fbcdn.net/v/t1.0-0/s526x296/50921805_1052818091564544_4142269564970860544_n.jpg?_nc_cat=103&_nc_ht=scontent.fpoa12-1.fna&oh=b2853440e04cda8580dc789259e76e36&oe=5D51BA00",
		"address": "Travessa Venezianos, 90050-370 Porto Alegre",
		"datetimes": [
			"2019-06-18 21:00:00"
		],
		"place": "Travessa Venezianos",
		"organizers": [
			"Cumbia na Rua - Bailando sin Fronteras",
			"Parrhesia R\u00e1dio Web & TV",
			"Instituto Parrhesia Erga Omnes",
			"CRAZY WORLD ARTS"
		],
		"organizers_fallback_a": [
			"Travessa Venezianos"
		],
		"description": "<span>Ent\u00e3o gente chegou o momento do corre aut\u00f4nomo viralizar o patrocinado...<br><br>vem com nois que vai ser loko....<br><br>Entonces vem com noisssss que a lua ta lindona, l\u00e1 no c\u00e9u.... vem cumbiar liga xs migxs.<br><br>Respeita os corre<br>respeita as mina<br><br>vem de bici<br><br>vem de bando<br><br>vem de boas....<br><br>Cada um cuida do seu lixooooooooooooooooo<br><br>Bebidinhas para todxs os  gostos.<br> <br></span>",
		"categories": [
			"Art"
		],
		"source_url": "https://www.facebook.com/events/387296818698077"
	},
	{
		"name": "Travessa Cultural V\u00e9spera de Feriado",
		"cover_url": "https://scontent.fpoa12-1.fna.fbcdn.net/v/t1.0-0/p403x403/56201239_1090753694437650_1946973997434404864_n.jpg?_nc_cat=103&_nc_ht=scontent.fpoa12-1.fna&oh=ec8e359ea37506810e3f5554aa75c619&oe=5D52C0BD",
		"address": "Travessa dos Venezianos n\u00b030, 90050370 Porto Alegre",
		"datetimes": [
			"2019-06-18 19:00:00"
		],
		"place": "Instituto Parrhesia Erga Omnes",
		"organizers": [
			"Cumbia na Rua - Bailando sin Fronteras",
			"Parrhesia R\u00e1dio Web & TV",
			"CRAZY WORLD ARTS"
		],
		"organizers_fallback_a": [
			"Instituto Parrhesia Erga Omnes"
		],
		"description": "<span>Oque? Travessa Cultural V\u00e9spera de Feriado<br>Quando? quinta feira 18 de abril.<br><br>Travessa Cultural V\u00e9spera de Feriado, chega com Abril que chegou chegando: - Ditadura nunca mais!!! Nessa pegada e pra abrir os caminhos resolvemos nos manifestar culturalmente, exercendo o direito constitucional da livre manifesta\u00e7\u00e3o,bolamos essa programa\u00e7\u00e3o linda de arte e resist\u00eancia para a Travessa Cultural V\u00e9spera de Feriado.<br><br>Com muita juventude, disposi\u00e7\u00e3o e autonomia, convidamos para Abrir nosso role, A Batalha da Liberdade que vem direto de Viam\u00e3o, pra trazer pra n\u00f3s, um pouquito da cena que rola na cidade.<br> <br>Na sequ\u00eancia um showza\u00e7o com a Mc Versa que atua fortemente nas batalhas de Floripa e vem tornando seu nome conhecido atrav\u00e9s dos seus sons de emponderamento feminino com muita for\u00e7a e garra. VERSA \u00e9 MC, compositora, oficineira e freestylera. Nascida em Seara - SC, atualmente, vive em Florian\u00f3polis, cidade onde participa e colabora na organiza\u00e7\u00e3o da Batalha das Minas, \u00e9 integrante do coletivo Trama Feminina e participa ativamente das batalhas de rima em todo Brasil. Suas letras retratam seu cotidiano como mulher e suas viv\u00eancias na rap, denunciando opress\u00f5es, e combatendo atitudes machistas. Valoriza muito essa conex\u00e3o com quem se identifica com sua m\u00fasica e busca ser uma incentivadora de mulheres. Andressa Versa  <a  href=\"https://www.facebook.com/hashtag/tramafeminina\">#tramafeminina</a>  <a  href=\"https://www.facebook.com/hashtag/rapdimina\">#rapdimina</a> <br><br><br>Pra encerrar a noite Muy Vaguitos Sound System do Colectivo Cumbia na Rua Bailando sin Fronteras,  com toda sua latinidade do ritmo mais caliente e hermoso.<br><br>Al\u00e9m disso tamo preparando uma atra\u00e7\u00e3o surpresa.... entonces se prepara e vem com n\u00f3is que vai ser lindoooooo...<br><br><br>Vem de boas<br>Vem de Bici<br>Vem de bando<br><br><a  href=\"https://www.facebook.com/hashtag/respeitaasmina\">#respeitaasmina</a><br><br><a  href=\"https://www.facebook.com/hashtag/respeitatodxs\">#respeitatodxs</a><br><br><a  href=\"https://www.facebook.com/hashtag/respeitaoscorre\">#respeitaoscorre</a><br><br><a  href=\"https://www.facebook.com/hashtag/preserveosespa\u00e7osokupados\">#preserveosespa\u00e7osokupados</a><br><br>Informa\u00e7\u00f5es complementares: <br><br><a  href=\"https://www.facebook.com/hashtag/tagsnight\">#tagsnight</a><br>A organiza\u00e7\u00e3o estar\u00e1 disponibilizando dois pain\u00e9is, para as tags da night, com o intuito de interagir com o publico de forma clara em uma linguagem que a travessa dos venezianos \u00e9 um local tombado pelo patrim\u00f4nio e esta aqui para ser okupada por todxs respeitando os  moradores e com\u00e9rcios locais. Entonces as responsabilidades s\u00e3o individuais e coletivas. Vem somar com noisss  chama xs migxs e da o papo reto que aqui todxs s\u00e3o bem vindxs.<br><br>Por que #tagsnight ?<br><br>H\u00e1 alguns meses rolou um evento por aqui na travessa, e acabou ocorrendo pixa\u00e7\u00f5es nas casas durante o evento. N\u00f3s da organiza\u00e7\u00e3o tivemos que assumir a responsabilidade dos atos e fazermos a repara\u00e7\u00e3o dos danos.<br>Nossos coletivos s\u00e3o oriundos de movimentos sociais perif\u00e9ricos, tendo entre seus integrantes minas, ex detentos e moradores de rua... ent\u00e3o nossa linguagem \u00e9 a mesma das tags do rap e das cumbias e todxs os outros ritmos que abra\u00e7amos. Vem com n\u00f3is e te soma nas lutas...<br><br>Durante o evento vai rolar feirinha de economia criativa e solidaria, interessadxs em participar liga nois no in box...<br><br>Links relacionados:<br><a  href=\"https://www.facebook.com/cumbianarua/\">Cumbia na Rua - Bailando sin Fronteras</a><br><a  href=\"https://www.facebook.com/BatalhaDaLiberdade/\">Batalha Da Liberdade</a><br>VERSA<br><a  href=\"https://www.facebook.com/batalhadomercado/\">Batalha Do Mercado</a><br><a  href=\"https://www.facebook.com/batalha.dasmonstras.3\">Batalha Das Monstras</a><br>Batalha do Gas\u00f4metro<br><a  href=\"https://www.facebook.com/groups/batalhaderimabrasil/\">Batalha de Rima Brasil</a><br><br><br><br></span>",
		"categories": [
			"Art"
		],
		"source_url": "https://www.facebook.com/events/403338487134274"
	},
	{
		"name": "Gastronomia & Arte no Parque - Edi\u00e7\u00e3o Dia das M\u00e3es.",
		"cover_url": "https://scontent.fpoa12-1.fna.fbcdn.net/v/t1.0-9/s720x720/55765339_2238312236417022_892635199295193088_n.jpg?_nc_cat=111&_nc_ht=scontent.fpoa12-1.fna&oh=8588b44741c5e87b658b6102f46fcdbd&oe=5D035089",
		"address": "91310-001 Porto Alegre",
		"datetimes": [
			"2019-05-05 11:00:00"
		],
		"place": "Parque Marcos Rubim",
		"organizers": [
			"Mega Revel - Feira Cultural"
		],
		"organizers_fallback_a": [
			"Parque Marcos Rubim"
		],
		"description": "<span>Mega Revel  - Feira Cultural edi\u00e7\u00e3o especial Dia das M\u00e3es.<br>\u2764\ufe0f\u2764\ufe0f\u2764\ufe0f<br><br>Venha fazer suas comprinhas para quem voc\u00ea Ama! \ud83e\udd70\ud83d\ude0d<br>Presente \u00fanico e Feito com Amor!<br><br>Os visitantes  poder\u00e3o prestigiar a nossa Feira Cultural com mais de 50 expositores locais com um grande Mix de Trabalhos e Marcas Autorais, dando espa\u00e7o a Economia Criativa e promovendo o desenvolvimento sustent\u00e1vel.<br><br><a  href=\"https://www.facebook.com/hashtag/valorizeoartesanatolocal\">#ValorizeoArtesanatoLocal</a><br><a  href=\"https://www.facebook.com/hashtag/compredequemfaz\">#CompredeQuemFaz</a><br>\u2764\ufe0f\u2764\ufe0f\u2764\ufe0f<br><br><a  href=\"https://www.facebook.com/hashtag/megarevel\">#MegaRevel</a><br><a  href=\"https://www.facebook.com/hashtag/feiracultural\">#FeiraCultural</a><br><a  href=\"https://www.facebook.com/hashtag/arte\">#Arte</a><br><a  href=\"https://www.facebook.com/hashtag/m\u00fasica\">#M\u00fasica</a><br><a  href=\"https://www.facebook.com/hashtag/gastronomia\">#Gastronomia</a><br><a  href=\"https://www.facebook.com/hashtag/cervejaartesanal\">#CervejaArtesanal</a><br><a  href=\"https://www.facebook.com/hashtag/diversidade\">#Diversidade</a><br><a  href=\"https://www.facebook.com/hashtag/modasustent\u00e1vel\">#ModaSustent\u00e1vel</a><br><a  href=\"https://www.facebook.com/hashtag/consumoconsciente\">#ConsumoConsciente</a><br><a  href=\"https://www.facebook.com/hashtag/eventolimpo\">#EventoLimpo</a><br><a  href=\"https://www.facebook.com/hashtag/lixozero\">#LixoZero</a><br><a  href=\"https://www.facebook.com/hashtag/vemproparque\">#VemProParque</a><br><br>REALIZA\u00c7\u00c3O:<br>Mega Revel - Feira Cultural   <br><br>APOIO:<br><a  href=\"https://www.facebook.com/asconjijardimitalia/\">Asconji</a><br><a  href=\"https://www.facebook.com/poanarua/\">Poa Na Rua</a><br><br>Aqui seu amigo Pet \u00e9 Bem Vindo!! \u2764\ufe0f\u2764\ufe0f\u2764\ufe0f<br><br>EVENTO FREE!!!<br><br>EM CASO DE CHUVA O EVENTO SER\u00c1 TRANSFERIDO.<br><br>Acompanhe a nossa p\u00e1gina Mega Revel - Feira Cultural.<br></span>",
		"categories": [
			"Crafts",
			"Kid Friendly",
			"Food festival"
		],
		"source_url": "https://www.facebook.com/events/2210284975745071"
	},
	{
		"name": "M\u00fasica na Pra\u00e7a J\u00falio Mesquita",
		"cover_url": "https://scontent.fpoa12-1.fna.fbcdn.net/v/t1.0-0/s552x414/53934081_2225345861046993_104727086681292800_n.jpg?_nc_cat=107&_nc_ht=scontent.fpoa12-1.fna&oh=cfaf9a9fae9882aaa8849e632c9f1c76&oe=5D46BE69",
		"address": "entre av. Jo\u00e3o Goulart e rua Gen. Salustiano, 90010-120 Porto Alegre",
		"datetimes": [
			"2019-05-01 11:00:00"
		],
		"place": "Pra\u00e7a J\u00falio Mesquita",
		"organizers": [
			"Mega Revel - Feira Cultural",
			"Encontro de Bandas"
		],
		"organizers_fallback_a": [
			"Pra\u00e7a J\u00falio Mesquita"
		],
		"description": "<span>Mais uma realiza\u00e7\u00e3o <a  href=\"https://www.facebook.com/MegaRevelRS/\">Mega Revel - Feira Cultural</a><br><br>Dessa vez chegamos na <a  href=\"https://www.facebook.com/pages/Pra\u00e7a-J\u00falio-Mesquita/541389312647062\">Pra\u00e7a J\u00falio Mesquita</a> com uma super edi\u00e7\u00e3o para curtir o mais Lindoo P\u00f4r do Sol para quem estiver em Porto Alegre!!.<br><br>Curtir o Findi com a Fam\u00edlia e os Amigos reunidos \u00e9 uma del\u00edcia. <br>Com M\u00fasica, Cerveja Artesanal e Comida boa ent\u00e3o, nem se fala! <br><br>Vamos dar Vida aos locais p\u00fablicos!!!<br>Vamos trazer a Arte e a M\u00fasica para as Pra\u00e7as e Parques!!! <br>\ud83c\udfad\ud83d\uddbc\ufe0f\ud83c\udfb6\ud83c\udfb8\ud83c\udfa7\ud83c\udfa4\ud83e\udd41\ud83c\udfbc<br><br><br>\u00c9 poss\u00edvel trazer Vida para as Pra\u00e7as??!!<br>Simm!!<br><br>Toda Cidade precisa de um lugar onde as pessoas possam se reunir e ouvir uma boa m\u00fasica. <br>\u00c9 bom pra quem canta, \u00e9 bom pra quem escuta. <br>Cultura \u00e9 isso, tem que estar nas ruas, tem que estar no meio do povo.<br><br>As Pra\u00e7as podem e devem ser ocupadas para o lazer, promovendo e favorecendo a Cultura. <br>Assim o p\u00fablico t\u00eam a oportunidade de viver algo diferente em um espa\u00e7o que acolhe a todos.<br><br>Nossos eventos s\u00e3o um espa\u00e7o de Diversidade, a onde todo G\u00eanero, Ra\u00e7a, Cor e Estilo s\u00e3o Bem Vindos.<br><br>Nosso objetivo \u00e9 ocupar mais os locais p\u00fablicos de Porto Alegre que est\u00e3o abandonados e esquecidos, trazendo assim mais vida para as Pra\u00e7as e Parques.<br><br>Os visitantes tamb\u00e9m poder\u00e3o prestigiar a nossa Feira Cultural com mais de 50 Expositores locais com Trabalhos e Marcas Autorais, dando espa\u00e7o a Economia Criativa e promovendo o desenvolvimento sustent\u00e1vel.<br><br><a  href=\"https://www.facebook.com/hashtag/megarevel\">#MegaRevel</a><br><a  href=\"https://www.facebook.com/hashtag/feiracultural\">#FeiraCultural</a><br><a  href=\"https://www.facebook.com/hashtag/modasustent\u00e1vel\">#ModaSustent\u00e1vel</a><br><a  href=\"https://www.facebook.com/hashtag/arte\">#Arte</a><br><a  href=\"https://www.facebook.com/hashtag/m\u00fasica\">#M\u00fasica</a><br><a  href=\"https://www.facebook.com/hashtag/gastronomia\">#Gastronomia</a><br><a  href=\"https://www.facebook.com/hashtag/cervejaartesanal\">#CervejaArtesanal</a><br><a  href=\"https://www.facebook.com/hashtag/eventolimpo\">#EventoLimpo</a><br><a  href=\"https://www.facebook.com/hashtag/consumoconsciente\">#ConsumoConsciente</a><br><a  href=\"https://www.facebook.com/hashtag/lixozero\">#LixoZero</a><br><a  href=\"https://www.facebook.com/hashtag/vemprapra\u00e7a\">#VemPraPra\u00e7a</a><br><br><br>Aqui seu amigo Pet \u00e9 Bem Vindo!! \u2665 \u2665<br><br>EVENTO FREE!!!<br><br>EM CASO DE CHUVA O EVENTO SER\u00c1 TRANSFERIDO.<br><br>Em breve divulgaremos todos os participantes aqui no Evento!!<br><br>Fica ligado!!<br><br>Acompanhe a nossa p\u00e1gina <a  href=\"https://www.facebook.com/MegaRevelRS/\">Mega Revel - Feira Cultural</a>.<br><br>APOIO: <a  href=\"https://www.facebook.com/poanarua/\">Poa Na Rua</a></span>",
		"categories": [
			"Party",
			"Kid Friendly",
			"Food festival"
		],
		"source_url": "https://www.facebook.com/events/1925308807547375"
	},
	{
		"name": "Edi\u00e7\u00e3o Especial - 4 Anos Mega Revel - Feira Cultural",
		"cover_url": "https://scontent.fpoa12-1.fna.fbcdn.net/v/t1.0-9/s720x720/53896997_2229232320658347_4501566209463943168_n.jpg?_nc_cat=107&_nc_ht=scontent.fpoa12-1.fna&oh=8d73ddb8016757c926595d6adc4c34bb&oe=5D4E5989",
		"address": "Rua Comendador Caminha, 90510-000 Porto Alegre",
		"datetimes": [
			"2019-06-28 10:00:00"
		],
		"place": "Parque Moinhos de Vento",
		"organizers": [
			"Mega Revel - Feira Cultural"
		],
		"organizers_fallback_a": [
			"Parque Moinhos de Vento"
		],
		"description": "<span>Venha comemorar conosco os 4 anos de Anivers\u00e1rio da <a  href=\"https://www.facebook.com/MegaRevelRS/\">Mega Revel - Feira Cultural</a>!!!<br><br>Em 2015 surgia um novo Evento de Rua ( Mega Bazar), que tinha como proposta apoiar o Artesanato e o Pequeno Empreendedor local.<br><br>O palco dessa primeira edi\u00e7\u00e3o foi um dos Parques mais lindos de Poa <a  href=\"https://www.facebook.com/groups/1585096695062621/\">Parc\u00e3o - Parque Moinhos de Vento</a>!!<br><br>De l\u00e1 pra c\u00e1 foram muitas edi\u00e7\u00f5es realizadas neste local, e nada mais do que justo que essa comemora\u00e7\u00e3o seja realizada aqui, local que nos acolheu na nossa 1\u00aa Edi\u00e7\u00e3o!!<br><br>O Evento cresceu, e conosco hoje nos acompanham mais de 200 Expositores locais com Trabalhos e Marcas Autorais, dando espa\u00e7o a Economia Criativa e promovendo o desenvolvimento sustent\u00e1vel.<br><br>A Mega Revel se tornou uma grande Feira Cultural, que tem como objetivo ocupar mais os espa\u00e7os p\u00fablicos de Poa, trazendo assim mais vida para as Pra\u00e7as e Parques, com M\u00fasica, Arte e Gastronomia!!<br><br><a  href=\"https://www.facebook.com/hashtag/megarevel\">#MegaRevel</a><br><a  href=\"https://www.facebook.com/hashtag/feiracultural\">#FeiraCultural</a><br><a  href=\"https://www.facebook.com/hashtag/modasustent\u00e1vel\">#ModaSustent\u00e1vel</a><br><a  href=\"https://www.facebook.com/hashtag/arte\">#Arte</a><br><a  href=\"https://www.facebook.com/hashtag/m\u00fasica\">#M\u00fasica</a><br><a  href=\"https://www.facebook.com/hashtag/gastronomia\">#Gastronomia</a><br><a  href=\"https://www.facebook.com/hashtag/cervejaartesanal\">#CervejaArtesanal</a><br><a  href=\"https://www.facebook.com/hashtag/eventolimpo\">#EventoLimpo</a><br><a  href=\"https://www.facebook.com/hashtag/consumoconsciente\">#ConsumoConsciente</a><br><a  href=\"https://www.facebook.com/hashtag/consumolocal\">#ConsumoLocal</a><br><a  href=\"https://www.facebook.com/hashtag/compredequemfaz\">#CompreDeQuemFaz</a><br><a  href=\"https://www.facebook.com/hashtag/lixozero\">#LixoZero</a><br><a  href=\"https://www.facebook.com/hashtag/vemproparque\">#VemProParque</a><br><a  href=\"https://www.facebook.com/hashtag/vempramegarevel\">#VemPraMegaRevel</a><br><br><br>Aqui seu amigo Pet \u00e9 Bem Vindo!! \u2665 \u2665 \ud83d\udc3e\ud83d\udc3e<br><br>EVENTO FREE!!!<br><br>EM CASO DE CHUVA O EVENTO SER\u00c1 TRANSFERIDO.<br><br>Em breve divulgaremos aqui no Evento todos os participantes e atra\u00e7\u00f5es especiais para esse grande dia!!<br><br>Fica ligado!!<br><br>Acompanhe a nossa p\u00e1gina <a  href=\"https://www.facebook.com/MegaRevelRS/\">Mega Revel - Feira Cultural</a><br>APOIO: <a  href=\"https://www.facebook.com/poanarua/\">Poa Na Rua</a><br></span>",
		"categories": [
			"Art",
			"Kid Friendly",
			"Food festival"
		],
		"source_url": "https://www.facebook.com/events/279301942737437"
	},
	{
		"name": "Edi\u00e7\u00e3o Especial de P\u00e1scoa - Menino Deus",
		"cover_url": "https://scontent.fpoa12-1.fna.fbcdn.net/v/t1.0-0/p235x350/55811474_2233745343540378_8653907683197321216_n.jpg?_nc_cat=111&_nc_ht=scontent.fpoa12-1.fna&oh=c2e781b6b5df7f030286dbc9aec67c22&oe=5D4884A9",
		"address": "Rua Vicente Lopes dos Santos, 90130-140 Porto Alegre",
		"datetimes": [
			"2019-06-21 11:00:00"
		],
		"place": "Praca estado de ISrael",
		"organizers": [
			"Mega Revel - Feira Cultural"
		],
		"organizers_fallback_a": [
			"Praca estado de ISrael"
		],
		"description": "<span><a  href=\"https://www.facebook.com/MegaRevelRS/\">Mega Revel - Feira Cultural</a> vem com uma edi\u00e7\u00e3o Especial de P\u00e1scoa!!!<br>\ud83d\ude0d\ud83d\ude0d\ud83d\udc30\ud83d\udc30<br><br>Edi\u00e7\u00e3o Especial P\u00e1scoa - Menino Deus.<br><br>Vem curtir o Domingo de P\u00e1scoa conosco!!<br><br>Convidem os Amigos, a Fam\u00edlia, tragam a Crian\u00e7ada, os Pets!!<br><br>Teremos v\u00e1rias atra\u00e7\u00f5es para Crian\u00e7ada!!<br><br>Espa\u00e7o Kids, Guloseimas e muito mais!!<br>\ud83d\ude31 \ud83c\udf6c\ud83c\udf6d\ud83c\udf6c\ud83c\udf6d \ud83d\ude31<br><br><a  href=\"https://www.facebook.com/hashtag/megarevel\">#MegaRevel</a><br><a  href=\"https://www.facebook.com/hashtag/feiracultural\">#FeiraCultural</a><br><a  href=\"https://www.facebook.com/hashtag/edi\u00e7\u00e3op\u00e1scoa\">#Edi\u00e7\u00e3oP\u00e1scoa</a><br><a  href=\"https://www.facebook.com/hashtag/espa\u00e7okids\">#Espa\u00e7oKids</a><br><a  href=\"https://www.facebook.com/hashtag/modasustent\u00e1vel\">#ModaSustent\u00e1vel</a><br><a  href=\"https://www.facebook.com/hashtag/arte\">#Arte</a><br><a  href=\"https://www.facebook.com/hashtag/m\u00fasica\">#M\u00fasica</a><br><a  href=\"https://www.facebook.com/hashtag/gastronomia\">#Gastronomia</a><br><a  href=\"https://www.facebook.com/hashtag/cervejaartesanal\">#CervejaArtesanal</a><br><a  href=\"https://www.facebook.com/hashtag/eventolimpo\">#EventoLimpo</a><br><a  href=\"https://www.facebook.com/hashtag/consumoconsciente\">#ConsumoConsciente</a><br><a  href=\"https://www.facebook.com/hashtag/lixozero\">#LixoZero</a><br><a  href=\"https://www.facebook.com/hashtag/vemprapra\u00e7a\">#VemPraPra\u00e7a</a><br><br>E \u00e9 claro, a nossa Feira Cultural com mais de 50 Expositores locais, com Trabalhos e Marcas Autorais, dando espa\u00e7o a Economia Criativa e ao Desenvolvimento Sustent\u00e1vel!!!!<br>\ud83d\ude0d\ud83d\ude0d\ud83d\ude31\ud83d\ude31\ud83d\ude31\ud83d\ude31\ud83d\ude31<br><br>Vai perder??<br><br>Aqui seu amigo Pet \u00e9 Bem Vindo!! \u2665 \u2665<br><br>REALIZA\u00c7\u00c3O:<br><a  href=\"https://www.facebook.com/MegaRevelRS/\">Mega Revel - Feira Cultural</a><br><br>APOIO:<br><a  href=\"https://www.facebook.com/poanarua/\">Poa Na Rua</a><br><br>EVENTO FREE!!!<br><br>EM CASO DE CHUVA O EVENTO SER\u00c1 TRANSFERIDO.<br></span>",
		"categories": [
			"Crafts",
			"Kid Friendly",
			"Food festival"
		],
		"source_url": "https://www.facebook.com/events/360702104543160"
	},
	{
		"name": "1\u00ba Festival Gastron\u00f4mico da Pra\u00e7a Cinquenten\u00e1rio da R\u00e1dio Ga\u00facha",
		"cover_url": "https://scontent.fpoa12-1.fna.fbcdn.net/v/t1.0-9/s720x720/53415084_2229233053991607_4510149302173040640_n.jpg?_nc_cat=103&_nc_ht=scontent.fpoa12-1.fna&oh=ce74e1ac3a57b2ba978bac77db073c20&oe=5D458FE6",
		"address": "Rua Saldanha Marinho, 90150-101 Porto Alegre",
		"datetimes": [
			"2019-06-14 11:00:00"
		],
		"place": "Pra\u00e7a Cinq\u00fcenten\u00e1rio Da R\u00e1dio Ga\u00facha",
		"organizers": [
			"Mega Revel - Feira Cultural"
		],
		"organizers_fallback_a": [
			"Pra\u00e7a Cinq\u00fcenten\u00e1rio Da R\u00e1dio Ga\u00facha"
		],
		"description": "<span>Vem novidade por ai!!!<br><br>A <a  href=\"https://www.facebook.com/MegaRevelRS/\">Mega Revel - Feira Cultural</a> chega na <a  href=\"https://www.facebook.com/pages/Pra\u00e7a-Cinq\u00fcenten\u00e1rio-Da-R\u00e1dio-Ga\u00facha/215959561820174\">Pra\u00e7a Cinq\u00fcenten\u00e1rio Da R\u00e1dio Ga\u00facha</a>.<br>\ud83c\udf1e\ud83d\udc68\u200d\ud83d\udc69\u200d\ud83d\udc66\ud83d\udc3e\ud83d\udc15\u2764\ufe0f<br><br>A Pra\u00e7a fica localizada no Bairro Menino Deus na Rua Saldanha Marinho.<br><br>Nosso objetivo \u00e9 ocupar mais os locais p\u00fablicos de Porto Alegre, trazendo assim mais Vida para as Pra\u00e7as e Parques.<br><br><br>Queremos reunir pessoas em s\u00f3 lugar, em um espa\u00e7o que acolha a todos, fomentando a Arte e a Cultura da nossa regi\u00e3o.<br><br><br>Os visitantes tamb\u00e9m poder\u00e3o prestigiar Trabalhos Autorais de Pequenos Empreendedores locais, dando espa\u00e7o a Economia Criativa e promovendo o desenvolvimento sustent\u00e1vel.<br><br><br>\u00c9 poss\u00edvel trazer vida para as Pra\u00e7as??!!<br><br>Sim!!<br><br>Toda cidade precisa de um lugar onde as pessoas possam se reunir e ouvir uma boa m\u00fasica. <br>\u00c9 bom pra quem canta, \u00e9 bom pra quem escuta. <br>Cultura \u00e9 isso, tem que estar nas ruas, tem que estar no meio do povo.<br>As Pra\u00e7as podem e devem ser ocupadas para o lazer, promovendo e favorecendo a Cultura. <br>Assim o p\u00fablico ter\u00e1 a oportunidade de viver algo diferente em um espa\u00e7o que acolhe a todos.<br><br>Nossos eventos s\u00e3o um espa\u00e7o de Diversidade, a onde toda a Cor, Ra\u00e7a, G\u00eanero e Estilo s\u00e3o Bem-Vindos.<br><br>Vai perder??<br><br>Pegue sua Canga, Cadeira de Praia, Chima, seu Pet e venha curtir O Domingo com os amigos e a fam\u00edlia!!! <br>\ud83c\udf1e\ud83d\udc68\u200d\ud83d\udc69\u200d\ud83d\udc66\ud83d\udc3e\ud83d\udc15\u2764\ufe0f<br><br>REALIZA\u00c7\u00c3O:<br><a  href=\"https://www.facebook.com/MegaRevelRS/\">Mega Revel - Feira Cultural</a><br><br><a  href=\"https://www.facebook.com/hashtag/megarevel\">#MegaRevel</a><br><a  href=\"https://www.facebook.com/hashtag/feiracultural\">#FeiraCultural</a><br><a  href=\"https://www.facebook.com/hashtag/modasustent\u00e1vel\">#ModaSustent\u00e1vel</a><br><a  href=\"https://www.facebook.com/hashtag/arte\">#Arte</a><br><a  href=\"https://www.facebook.com/hashtag/m\u00fasica\">#M\u00fasica</a><br><a  href=\"https://www.facebook.com/hashtag/diversidade\">#Diversidade</a><br><a  href=\"https://www.facebook.com/hashtag/gastronomia\">#Gastronomia</a><br><a  href=\"https://www.facebook.com/hashtag/cervejaartesanal\">#CervejaArtesanal</a><br><a  href=\"https://www.facebook.com/hashtag/eventolimpo\">#EventoLimpo</a><br><a  href=\"https://www.facebook.com/hashtag/consumoconsciente\">#ConsumoConsciente</a><br><a  href=\"https://www.facebook.com/hashtag/lixozero\">#LixoZero</a><br><a  href=\"https://www.facebook.com/hashtag/sustentabilidade\">#Sustentabilidade</a><br><a  href=\"https://www.facebook.com/hashtag/vemproparque\">#VemProParque</a><br><br>Aqui seu amigo Pet \u00e9 Bem Vindo!! \ud83d\udc3e\ud83d\udc15 \u2665 \u2665<br><br>EVENTO FREE!!!<br><br>EM CASO DE CHUVA O EVENTO SER\u00c1 TRANSFERIDO.<br><br>Acompanhe a nossa p\u00e1gina <a  href=\"https://www.facebook.com/MegaRevelRS/\">Mega Revel - Feira Cultural</a></span>",
		"categories": [
			"Food",
			"Kid Friendly",
			"Food festival"
		],
		"source_url": "https://www.facebook.com/events/2038361436218484"
	},
	{
		"name": "Baco Exu do Blues :: Opini\u00e3o",
		"cover_url": "https://scontent.fpoa12-1.fna.fbcdn.net/v/t1.0-0/s526x296/56472425_2301961959856287_6038351494187581440_n.jpg?_nc_cat=108&_nc_ht=scontent.fpoa12-1.fna&oh=6b5c4ea123bfe5cc921d19794e7a09da&oe=5D6B30A9",
		"address": "Jos\u00e9 Do Patroc\u00ednio, 90050-002 Porto Alegre",
		"datetimes": [
			"2019-06-11 23:00:00"
		],
		"place": "Bar Opini\u00e3o",
		"organizers": [
			"No Palco",
			"Opini\u00e3o Produtora",
			"Baco Exu do Blues"
		],
		"organizers_fallback_a": [
			"Bar Opini\u00e3o"
		],
		"description": "<span>Uma das sensa\u00e7\u00f5es da m\u00fasica brasileira na atualidade, o rapper Baco Exu do Blues ir\u00e1 trazer ao Opini\u00e3o, no dia 11 de abril, a turn\u00ea do seu aclamado segundo trabalho de est\u00fadio, chamado \u201cBluesman\u201d.<br><br>Baco Exu do Blues<br>Quinta-feira, dia 11 de abril, a partir das 23h<br>Bar Opini\u00e3o (Rua Jos\u00e9 do Patroc\u00ednio, 834)<br>Abertura da casa: 21h30<br>Classifica\u00e7\u00e3o: 16 anos<br>Realiza\u00e7\u00e3o: Opini\u00e3o Produtora<br><br>Ingressos:<br><br>Lote 1 [ESGOTADO]:<br>Promocional (valor reduzido, com a doa\u00e7\u00e3o de 1kg de alimento n\u00e3o perec\u00edvel, dispon\u00edvel para qualquer pessoa): R$ 55<br>Estudantes e idosos (desconto de 50%): R$ 50<br>Inteira: R$ 100<br><br>Lote 2 [ESGOTADO]:<br>Promocional (valor reduzido, com a doa\u00e7\u00e3o de 1kg de alimento n\u00e3o perec\u00edvel, dispon\u00edvel para qualquer pessoa): R$ 65<br>Estudantes e idosos (desconto de 50%): R$ 60<br>Inteira: R$ 120<br><br>Lote 3 [ESGOTADO]:<br>Promocional (valor reduzido, com a doa\u00e7\u00e3o de 1kg de alimento n\u00e3o perec\u00edvel, dispon\u00edvel para qualquer pessoa): R$ 75<br>Estudantes e idosos (desconto de 50%): R$ 70<br>Inteira: R$ 140<br><br>Lote 4 [ESGOTADO]:<br>Promocional (valor reduzido, com a doa\u00e7\u00e3o de 1kg de alimento n\u00e3o perec\u00edvel, dispon\u00edvel para qualquer pessoa): R$ 85<br>Estudantes e idosos (desconto de 50%): R$ 80<br>Inteira: R$ 160<br><br>* Os alimentos dever\u00e3o ser entregues no Opini\u00e3o, no momento da entrada ao evento.<br><br>** Para o benef\u00edcio da meia-entrada (50% de desconto), \u00e9 necess\u00e1ria a apresenta\u00e7\u00e3o da Carteira de Identifica\u00e7\u00e3o Estudantil (CIE) na entrada do espet\u00e1culo. Os documentos aceitos como v\u00e1lidos est\u00e3o determinados na Lei Federal 12.933/13.<br><br>Demais descontos:<br><br>* 50% para idosos: Lei Federal 10.741/03 \u2013 obrigat\u00f3ria apresenta\u00e7\u00e3o de identidade ou documento oficial com foto<br><br>* 50% para jovens pertencentes a fam\u00edlias de baixa renda: Lei Federal 12.933/13 \u2013 obrigat\u00f3ria apresenta\u00e7\u00e3o da Carteira de Identidade Jovem e de documento oficial com foto<br><br>* 50% para pessoas com defici\u00eancia (e acompanhante quando necess\u00e1rio): Lei Federal 12.933/13 \u2013 obrigat\u00f3ria apresenta\u00e7\u00e3o do Cart\u00e3o de Benef\u00edcio de Presta\u00e7\u00e3o Continuada da Assist\u00eancia Social da Pessoa com Defici\u00eancia ou de documento emitido pelo Instituto Nacional do Seguro Social (INSS)<br><br>Informa\u00e7\u00f5es:<br><a  href=\"http://www.opiniao.com.br/\" rel=\"nofollow\" >www.opiniao.com.br</a><br><a  href=\"https://www.facebook.com/opiniao.produtora/\">www.facebook.com/opiniao.produtora</a><br><a  href=\"https://www.twitter.com/opiniao\" rel=\"nofollow\" >www.twitter.com/opiniao</a><br>(51) 3211-2838</span>",
		"categories": [
			"Music"
		],
		"source_url": "https://www.facebook.com/events/2355968627965882"
	}
]